COPYING
MANIFEST.in
Makefile
NEWS
README.txt
VERSION.py
__pkginfo__.py
import_relative.py
make-check-filter.py
setup.cfg
setup.py
import_relative.egg-info/PKG-INFO
import_relative.egg-info/SOURCES.txt
import_relative.egg-info/dependency_links.txt
import_relative.egg-info/top_level.txt
test/Makefile
test/test-basic.py