Metadata-Version: 1.0
Name: import-relative
Version: 0.2.3
Summary: A different kind of relative import
Home-page: http://code.google.com/p/pyimport-relative
Author: Rocky Bernstein
Author-email: rocky@gnu.org
License: UNKNOWN
Platform: UNKNOWN
Classifier: Development Status :: 4 - Beta
Classifier: Intended Audience :: Developers
Classifier: License :: OSI Approved :: GNU General Public License (GPL)
Classifier: Programming Language :: Python
Classifier: Topic :: Software Development :: Libraries :: Python Modules
